flconverters/__init__.py
flconverters/flconverters.py
flconverters-1.1.3.dist-info/LICENSE
flconverters-1.1.3.dist-info/METADATA
flconverters-1.1.3.dist-info/WHEEL
flconverters-1.1.3.dist-info/top_level.txt
flconverters-1.1.3.dist-info/RECORD
