Metadata-Version: 2.1
Name: flconverters
Version: 1.1.3
Summary: Multiple file converters
Home-page: https://github.com/CSynodinos/converters
Author: Christos Synodinos
Author-email: chris_sinodinos@outlook.com
License: UNKNOWN
Platform: UNKNOWN
Classifier: Programming Language :: Python :: 3
Classifier: License :: OSI Approved :: MIT License
Classifier: Operating System :: OS Independent
Requires-Python: >=3.6
Requires-Dist: opencv-python (>=4.5.4.60)
Requires-Dist: pillow (>=8.4.0)
Requires-Dist: pandas (>=1.3.4)
Requires-Dist: rawpy (>=0.16.0)
Requires-Dist: docx (>=0.2.4)
Requires-Dist: tqdm (>=4.62.3)
Requires-Dist: XlsxWriter (>=3.0.2)
